drf_action_permissions/__init__.py
drf_action_permissions/permissions.py
drf_action_permissions-0.1.1.dist-info/WHEEL
drf_action_permissions-0.1.1.dist-info/METADATA
drf_action_permissions-0.1.1.dist-info/RECORD
